Metadata-Version: 2.1
Name: betterjson-python
Version: 0.1.0
Summary: BetterJSON is an enhanced version of the JSON data format
Home-page: https://github.com/ruxixa/BetterJSON
Author: Jan Kowalski
Author-email: a@a.com
Project-URL: Source, https://github.com/ruxixa/BetterJSON
Project-URL: Bug Reports, https://github.com/ruxixa/BetterJSON/issues
Keywords: kilka,słów,kluczowych,opisujących,Twoją,bibliotekę
Classifier: Programming Language :: Python
Requires-Python: >=3.0
